{"version":1,"resource":"vscode-remote://wsl%2Bubuntu-24.04/home/almir/escoladanuvem/pratica-02/calculadora_consumo_combustivel.py","entries":[{"id":"sKd3.py","timestamp":1747786542798},{"id":"Yr2c.py","timestamp":1747786750382},{"id":"ksML.py","timestamp":1747786795546},{"id":"fn1P.py","timestamp":1747786882489},{"id":"1OwR.py","timestamp":1747787042855},{"id":"Dnmb.py","timestamp":1747787070828},{"id":"hFoq.py","timestamp":1747787236751},{"id":"BjYF.py","timestamp":1747787283159},{"id":"SE8g.py","timestamp":1747787314179},{"id":"D0Zv.py","timestamp":1747787369855},{"id":"GN1V.py","timestamp":1747787386847},{"id":"YuEy.py","timestamp":1747787415976},{"id":"GouW.py","timestamp":1747787631082}]}